nostream_exporter/collector.py
nostream_exporter-0.0.2.dist-info/LICENSE
nostream_exporter-0.0.2.dist-info/METADATA
nostream_exporter-0.0.2.dist-info/WHEEL
nostream_exporter-0.0.2.dist-info/entry_points.txt
nostream_exporter-0.0.2.dist-info/top_level.txt
nostream_exporter-0.0.2.dist-info/RECORD
