Metadata-Version: 2.1
Name: nostream-exporter
Version: 0.0.2
Summary: Devops monitoring tool for Nostream
Author-email: blee <blee@bitcoiner.social>
License: Apache License
Project-URL: Homepage, https://github.com/bleetube/nostream_exporter
Keywords: nostream
Classifier: Programming Language :: Python
Classifier: Programming Language :: Python :: 3
Classifier: Programming Language :: Python :: 3.10
Classifier: Programming Language :: Python :: Implementation :: CPython
Classifier: Programming Language :: Python :: Implementation :: PyPy
Classifier: Topic :: System :: Monitoring
Classifier: License :: OSI Approved :: Apache Software License
Requires-Python: >=3.10.0
License-File: LICENSE
Requires-Dist: build (>=0.8.0)
Requires-Dist: prometheus-client (>=0.16.0)
Requires-Dist: psycopg2 (>=2.9.5)
